netgdb_proxy/__init__.py
netgdb_proxy/daemon.py
netgdb_proxy/debugnet.py
netgdb_proxy/debugnet_socket.py
netgdb_proxy/herald_listener.py
netgdb_proxy/logger.py
netgdb_proxy/profiler.py
netgdb_proxy/proxy.py
netgdb_proxy/single.py
netgdb_proxy/util.py
netgdb_proxy-1.0.0.dist-info/LICENSE
netgdb_proxy-1.0.0.dist-info/METADATA
netgdb_proxy-1.0.0.dist-info/WHEEL
netgdb_proxy-1.0.0.dist-info/entry_points.txt
netgdb_proxy-1.0.0.dist-info/RECORD
