Metadata-Version: 2.1
Name: netgdb-proxy
Version: 1.0.0
Summary: Proxy script for NetGDB
Home-page: https://github.com/dell/netgdb-proxy
License: BSD 2-Clause License
Author: John Reimer
Author-email: John_Reimer@Dell.com
Requires-Python: >=3.10,<4.0
Classifier: License :: Other/Proprietary License
Classifier: Programming Language :: Python :: 3
Classifier: Programming Language :: Python :: 3.10
Classifier: Programming Language :: Python :: 3.11
Provides-Extra: daemon
Requires-Dist: python-daemon (>=3.0.1,<4.0.0) ; extra == "daemon"
Project-URL: Repository, https://github.com/dell/netgdb-proxy
